README.md
setup.py
styles/Style.py
styles/__init__.py
styles/figures.py
styles/osInfo.py
styles.egg-info/PKG-INFO
styles.egg-info/SOURCES.txt
styles.egg-info/dependency_links.txt
styles.egg-info/top_level.txt