Metadata-Version: 2.1
Name: styles
Version: 0.1.8
Summary: A Style pack for python
Home-page: https://github.com/Xtarii/PythonStylePack
Author: Lord Alvin Hansen
Author-email: alvin.hansen@elev.ga.ntig.se
License: BSD 2-clause
Classifier: Development Status :: 1 - Planning
Classifier: Intended Audience :: Science/Research
Classifier: License :: OSI Approved :: BSD License
Classifier: Operating System :: POSIX :: Linux
Classifier: Programming Language :: Python :: 3.7
Classifier: Programming Language :: Python :: 3.11
